Metadata-Version: 2.1
Name: ggary-distributions
Version: 0.2
Summary: Gaussian Binomial Distribution
Home-page: UNKNOWN
Author: G Gary
Author-email: garethhao@gmail.com
License: UNKNOWN
Platform: UNKNOWN
